{
  "kind": "collectionType",
  "collectionName": "editoriales",
  "info": {
    "singularName": "editorial",
    "pluralName": "editoriales",
    "displayName": "Product · Libro · Editorial",
    "description": "Catálogo de editoriales disponibles"
  },
  "options": {
    "draftAndPublish": true
  },
  "pluginOptions": {},
  "attributes": {
    "id_editorial": {
      "type": "integer",
      "required": true,
      "unique": true
    },
    "nombre_editorial": {
      "type": "string",
      "required": true
    },
    "logo": {
      "type": "media",
      "multiple": false,
      "allowedTypes": [
        "images",
        "files",
        "videos",
        "audios"
      ]
    },
    "acronimo": {
      "type": "string"
    },
    "website": {
      "type": "string"
    },
    "sellos": {
      "type": "relation",
      "relation": "oneToMany",
      "target": "api::sello.sello",
      "mappedBy": "editorial"
    },
    "colecciones": {
      "type": "relation",
      "relation": "oneToMany",
      "target": "api::coleccion.coleccion",
      "mappedBy": "editorial"
    },
    "libros": {
      "type": "relation",
      "relation": "oneToMany",
      "target": "api::libro.libro",
      "mappedBy": "editorial"
    },
    "externalIds": {
      "type": "json",
      "description": "IDs externos de WooCommerce: { woo_moraleja: 123, woo_escolar: 456 }"
    }
  }
}
